orthomasker/__init__.py
orthomasker/cli.py
orthomasker/feature_extractor.py
orthomasker/mask_generator.py
orthomasker-1.0.2.dist-info/licenses/LICENSE
orthomasker-1.0.2.dist-info/METADATA
orthomasker-1.0.2.dist-info/WHEEL
orthomasker-1.0.2.dist-info/entry_points.txt
orthomasker-1.0.2.dist-info/top_level.txt
orthomasker-1.0.2.dist-info/RECORD
