Metadata-Version: 2.4
Name: orthomasker
Version: 1.0.2
Summary: A CLI tool and Python library for extracting vector features from geospatial raster (TIF) files using Meta AI's Segment Anything Model (SAM), and exporting them as GeoJSON output.
Author: Nicholas McCarty
Author-email: nick@upskilled.consulting
License: Apache-2.0
Project-URL: Homepage, https://github.com/nickmccarty/orthomasker
Project-URL: Repository, https://github.com/nickmccarty/orthomasker
Project-URL: Issues, https://github.com/nickmccarty/orthomasker/issues
Keywords: gis,geojson,tif,mask,cli
Classifier: Development Status :: 3 - Alpha
Classifier: Intended Audience :: Developers
Classifier: License :: OSI Approved :: Apache Software License
Classifier: Programming Language :: Python :: 3
Classifier: Programming Language :: Python :: 3.8
Classifier: Programming Language :: Python :: 3.9
Classifier: Programming Language :: Python :: 3.10
Classifier: Programming Language :: Python :: 3.11
Classifier: Programming Language :: Python :: 3.12
Requires-Python: >=3.8
License-File: LICENSE
Requires-Dist: click>=8.0.0
Requires-Dist: GDAL>=3.8.0
Requires-Dist: geopandas>=1.0.0
Requires-Dist: matplotlib>=3.10.0
Requires-Dist: numpy>=2.0.0
Requires-Dist: opencv-contrib-python>=4.11.0
Requires-Dist: opencv-python>=4.11.0
Requires-Dist: opencv-python-headless>=4.11.0
Requires-Dist: pandas>=2.2.0
Requires-Dist: pillow>=11.2.0
Requires-Dist: rasterio>=1.4.0
Requires-Dist: shapely>=2.1.0
Requires-Dist: geojson>=3.0.0
Requires-Dist: sam-wrapper>=0.1.1
Provides-Extra: dev
Requires-Dist: pytest>=7.0.0; extra == "dev"
Requires-Dist: pytest-cov>=4.0.0; extra == "dev"
Requires-Dist: black>=22.0.0; extra == "dev"
Requires-Dist: flake8>=5.0.0; extra == "dev"
Requires-Dist: mypy>=1.0.0; extra == "dev"
Requires-Dist: openpyxl>=3.1.0; extra == "dev"
Provides-Extra: ml
Dynamic: license-file
